[{
    "id": 123,
    "gender": 0,
    "age": 24,
    "price_level": 4,
    "restaurant": 1,
    "lodging": 1,
    "food": 1,
    "point_of_interest": 0,
    "establishment": 0,
    "bar": 0,
    "cafe": 1,
    "health": 1,
    "gym": 1,
    "placeId": 1
  }, {
    "id": 123,
    "gender": 0,
    "age": 24,
    "price_level": 4,
    "restaurant": 1,
    "lodging": 1,
    "food": 1,
    "point_of_interest": 0,
    "establishment": 0,
    "bar": 0,
    "cafe": 1,
    "health": 1,
    "gym": 1,
    "placeId": 2
  },
  {
    "id": 123,
    "gender": 0,
    "age": 24,
    "price_level": 4,
    "restaurant": 1,
    "lodging": 1,
    "food": 1,
    "point_of_interest": 0,
    "establishment": 0,
    "bar": 0,
    "cafe": 1,
    "health": 1,
    "gym": 1,
    "placeId": 3
  },
  {
    "id": 123,
    "gender": 0,
    "age": 24,
    "price_level": 4,
    "restaurant": 1,
    "lodging": 1,
    "food": 1,
    "point_of_interest": 0,
    "establishment": 0,
    "bar": 0,
    "cafe": 1,
    "health": 1,
    "gym": 1,
    "placeId": 4
  },
  {
    "id": 123,
    "gender": 0,
    "age": 24,
    "price_level": 4,
    "restaurant": 1,
    "lodging": 1,
    "food": 1,
    "point_of_interest": 0,
    "establishment": 0,
    "bar": 0,
    "cafe": 1,
    "health": 1,
    "gym": 1,
    "placeId": 5
  },
  {
    "id": 123,
    "gender": 1,
    "age": 20,
    "price_level": 1,
    "restaurant": 1,
    "lodging": 1,
    "food": 1,
    "point_of_interest": 0,
    "establishment": 0,
    "bar": 0,
    "cafe": 0,
    "health": 1,
    "gym": 0,
    "placeId": 7
  },
  {
    "id": 123,
    "gender": 0,
    "age": 24,
    "price_level": 2,
    "restaurant": 1,
    "lodging": 1,
    "food": 1,
    "point_of_interest": 0,
    "establishment": 0,
    "bar": 1,
    "cafe": 1,
    "health": 1,
    "gym": 1,
    "placeId": 6
  },
  {
    "id": 123,
    "gender": 0,
    "age": 26,
    "price_level": 4,
    "restaurant": 1,
    "lodging": 1,
    "food": 1,
    "point_of_interest": 0,
    "establishment": 0,
    "bar": 0,
    "cafe": 1,
    "health": 1,
    "gym": 1,
    "placeId": 4
  },
  {
    "id": 123,
    "gender": 1,
    "age": 22,
    "price_level": 4,
    "restaurant": 1,
    "lodging": 1,
    "food": 1,
    "point_of_interest": 0,
    "establishment": 0,
    "bar": 0,
    "cafe": 1,
    "health": 0,
    "gym": 1,
    "placeId": 4
  },
  {
    "id": 123,
    "gender": 1,
    "age": 23,
    "price_level": 4,
    "restaurant": 1,
    "lodging": 1,
    "food": 1,
    "point_of_interest": 0,
    "establishment": 0,
    "bar": 0,
    "cafe": 1,
    "health": 0,
    "gym": 1,
    "placeId": 4
  }
]